{"id": 442, "name": "spiritomb", "types": [{"slot": 1, "type": {"name": "ghost", "url": "https://pokeapi.co/api/v2/type/8/"}}, {"slot": 2, "type": {"name": "dark", "url": "https://pokeapi.co/api/v2/type/17/"}}], "stats": [{"base_stat": 50, "effort": 0, "stat": {"name": "hp", "url": "https://pokeapi.co/api/v2/stat/1/"}}, {"base_stat": 92, "effort": 0, "stat": {"name": "attack", "url": "https://pokeapi.co/api/v2/stat/2/"}}, {"base_stat": 108, "effort": 1, "stat": {"name": "defense", "url": "https://pokeapi.co/api/v2/stat/3/"}}, {"base_stat": 92, "effort": 0, "stat": {"name": "special-attack", "url": "https://pokeapi.co/api/v2/stat/4/"}}, {"base_stat": 108, "effort": 1, "stat": {"name": "special-defense", "url": "https://pokeapi.co/api/v2/stat/5/"}}, {"base_stat": 35, "effort": 0, "stat": {"name": "speed", "url": "https://pokeapi.co/api/v2/stat/6/"}}], "abilities": [{"ability": {"name": "pressure", "url": "https://pokeapi.co/api/v2/ability/46/"}, "is_hidden": false, "slot": 1}, {"ability": {"name": "infiltrator", "url": "https://pokeapi.co/api/v2/ability/151/"}, "is_hidden": true, "slot": 3}], "sprites": {"front_default": "https://raw.githubusercontent.com/PokeAPI/sprites/master/sprites/pokemon/442.png"}, "moves": [{"move": {"name": "body-slam"}, "earliest_level": null}, {"move": {"name": "disable"}, "earliest_level": null}, {"move": {"name": "psybeam"}, "earliest_level": null}, {"move": {"name": "hyper-beam"}, "earliest_level": null}, {"move": {"name": "toxic"}, "earliest_level": null}, {"move": {"name": "psychic"}, "earliest_level": null}, {"move": {"name": "hypnosis"}, "earliest_level": 6}, {"move": {"name": "night-shade"}, "earliest_level": 1}, {"move": {"name": "double-team"}, "earliest_level": null}, {"move": {"name": "smokescreen"}, "earliest_level": null}, {"move": {"name": "confuse-ray"}, "earliest_level": 1}, {"move": {"name": "dream-eater"}, "earliest_level": 19}, {"move": {"name": "flash"}, "earliest_level": null}, {"move": {"name": "rest"}, "earliest_level": null}, {"move": {"name": "substitute"}, "earliest_level": null}, {"move": {"name": "thief"}, "earliest_level": null}, {"move": {"name": "nightmare"}, "earliest_level": null}, {"move": {"name": "snore"}, "earliest_level": null}, {"move": {"name": "curse"}, "earliest_level": 1}, {"move": {"name": "spite"}, "earliest_level": 1}, {"move": {"name": "protect"}, "earliest_level": null}, {"move": {"name": "scary-face"}, "earliest_level": null}, {"move": {"name": "feint-attack"}, "earliest_level": 7}, {"move": {"name": "destiny-bond"}, "earliest_level": null}, {"move": {"name": "icy-wind"}, "earliest_level": null}, {"move": {"name": "endure"}, "earliest_level": null}, {"move": {"name": "swagger"}, "earliest_level": null}, {"move": {"name": "attract"}, "earliest_level": null}, {"move": {"name": "sleep-talk"}, "earliest_level": null}, {"move": {"name": "return"}, "earliest_level": null}, {"move": {"name": "frustration"}, "earliest_level": null}, {"move": {"name": "pain-split"}, "earliest_level": null}, {"move": {"name": "pursuit"}, "earliest_level": 1}, {"move": {"name": "hidden-power"}, "earliest_level": null}, {"move": {"name": "rain-dance"}, "earliest_level": null}, {"move": {"name": "sunny-day"}, "earliest_level": null}, {"move": {"name": "psych-up"}, "earliest_level": null}, {"move": {"name": "shadow-ball"}, "earliest_level": 43}, {"move": {"name": "uproar"}, "earliest_level": null}, {"move": {"name": "torment"}, "earliest_level": null}, {"move": {"name": "will-o-wisp"}, "earliest_level": null}, {"move": {"name": "memento"}, "earliest_level": 30}, {"move": {"name": "facade"}, "earliest_level": null}, {"move": {"name": "taunt"}, "earliest_level": null}, {"move": {"name": "helping-hand"}, "earliest_level": null}, {"move": {"name": "trick"}, "earliest_level": null}, {"move": {"name": "skill-swap"}, "earliest_level": null}, {"move": {"name": "imprison"}, "earliest_level": null}, {"move": {"name": "grudge"}, "earliest_level": null}, {"move": {"name": "snatch"}, "earliest_level": null}, {"move": {"name": "secret-power"}, "earliest_level": null}, {"move": {"name": "rock-tomb"}, "earliest_level": null}, {"move": {"name": "silver-wind"}, "earliest_level": null}, {"move": {"name": "extrasensory"}, "earliest_level": 25}, {"move": {"name": "calm-mind"}, "earliest_level": null}, {"move": {"name": "shock-wave"}, "earliest_level": null}, {"move": {"name": "water-pulse"}, "earliest_level": null}, {"move": {"name": "natural-gift"}, "earliest_level": null}, {"move": {"name": "payback"}, "earliest_level": 15}, {"move": {"name": "embargo"}, "earliest_level": null}, {"move": {"name": "sucker-punch"}, "earliest_level": 31}, {"move": {"name": "dark-pulse"}, "earliest_level": 34}, {"move": {"name": "giga-impact"}, "earliest_level": null}, {"move": {"name": "nasty-plot"}, "earliest_level": 18}, {"move": {"name": "shadow-sneak"}, "earliest_level": 1}, {"move": {"name": "trick-room"}, "earliest_level": null}, {"move": {"name": "captivate"}, "earliest_level": null}, {"move": {"name": "ominous-wind"}, "earliest_level": 25}, {"move": {"name": "wonder-room"}, "earliest_level": null}, {"move": {"name": "psyshock"}, "earliest_level": null}, {"move": {"name": "telekinesis"}, "earliest_level": null}, {"move": {"name": "foul-play"}, "earliest_level": null}, {"move": {"name": "round"}, "earliest_level": null}, {"move": {"name": "stored-power"}, "earliest_level": null}, {"move": {"name": "ally-switch"}, "earliest_level": null}, {"move": {"name": "hex"}, "earliest_level": 11}, {"move": {"name": "quash"}, "earliest_level": null}, {"move": {"name": "retaliate"}, "earliest_level": null}, {"move": {"name": "snarl"}, "earliest_level": null}, {"move": {"name": "phantom-force"}, "earliest_level": null}, {"move": {"name": "confide"}, "earliest_level": null}, {"move": {"name": "infestation"}, "earliest_level": null}, {"move": {"name": "burning-jealousy"}, "earliest_level": null}, {"move": {"name": "lash-out"}, "earliest_level": null}, {"move": {"name": "poltergeist"}, "earliest_level": null}, {"move": {"name": "tera-blast"}, "earliest_level": null}], "species": {"url": "https://pokeapi.co/api/v2/pokemon-species/442/"}, "height": 10, "weight": 1080}