{"flavor_text_entries": [{"flavor_text": "This mysterious Pok\u00e9mon has some similarities to a creature that an old book introduced as Slither Wing.", "language": {"name": "en", "url": "https://pokeapi.co/api/v2/language/9/"}, "version": {"name": "scarlet", "url": "https://pokeapi.co/api/v2/version/40/"}}, {"flavor_text": "This Pok\u00e9mon somewhat resembles an ancient form of Volcarona that was introduced in a dubious magazine.", "language": {"name": "en", "url": "https://pokeapi.co/api/v2/language/9/"}, "version": {"name": "violet", "url": "https://pokeapi.co/api/v2/version/41/"}}], "evolution_chain": {"url": "https://pokeapi.co/api/v2/evolution-chain/519/"}}