{"id": 10067, "name": "altaria-mega", "types": [{"slot": 1, "type": {"name": "dragon", "url": "https://pokeapi.co/api/v2/type/16/"}}, {"slot": 2, "type": {"name": "fairy", "url": "https://pokeapi.co/api/v2/type/18/"}}], "stats": [{"base_stat": 75, "effort": 0, "stat": {"name": "hp", "url": "https://pokeapi.co/api/v2/stat/1/"}}, {"base_stat": 110, "effort": 0, "stat": {"name": "attack", "url": "https://pokeapi.co/api/v2/stat/2/"}}, {"base_stat": 110, "effort": 0, "stat": {"name": "defense", "url": "https://pokeapi.co/api/v2/stat/3/"}}, {"base_stat": 110, "effort": 0, "stat": {"name": "special-attack", "url": "https://pokeapi.co/api/v2/stat/4/"}}, {"base_stat": 105, "effort": 2, "stat": {"name": "special-defense", "url": "https://pokeapi.co/api/v2/stat/5/"}}, {"base_stat": 80, "effort": 0, "stat": {"name": "speed", "url": "https://pokeapi.co/api/v2/stat/6/"}}], "abilities": [{"ability": {"name": "pixilate", "url": "https://pokeapi.co/api/v2/ability/182/"}, "is_hidden": false, "slot": 1}], "sprites": {"front_default": "https://raw.githubusercontent.com/PokeAPI/sprites/master/sprites/pokemon/10067.png"}, "moves": [{"move": {"name": "fly"}, "earliest_level": null}, {"move": {"name": "fury-attack"}, "earliest_level": 7}, {"move": {"name": "take-down"}, "earliest_level": 23}, {"move": {"name": "growl"}, "earliest_level": 1}, {"move": {"name": "roar"}, "earliest_level": null}, {"move": {"name": "sing"}, "earliest_level": 1}, {"move": {"name": "flamethrower"}, "earliest_level": null}, {"move": {"name": "mist"}, "earliest_level": 14}, {"move": {"name": "ice-beam"}, "earliest_level": null}, {"move": {"name": "hyper-beam"}, "earliest_level": null}, {"move": {"name": "peck"}, "earliest_level": 1}, {"move": {"name": "solar-beam"}, "earliest_level": null}, {"move": {"name": "earthquake"}, "earliest_level": null}, {"move": {"name": "toxic"}, "earliest_level": null}, {"move": {"name": "double-team"}, "earliest_level": null}, {"move": {"name": "fire-blast"}, "earliest_level": null}, {"move": {"name": "dream-eater"}, "earliest_level": null}, {"move": {"name": "sky-attack"}, "earliest_level": 1}, {"move": {"name": "rest"}, "earliest_level": null}, {"move": {"name": "substitute"}, "earliest_level": null}, {"move": {"name": "thief"}, "earliest_level": null}, {"move": {"name": "snore"}, "earliest_level": null}, {"move": {"name": "protect"}, "earliest_level": null}, {"move": {"name": "perish-song"}, "earliest_level": 46}, {"move": {"name": "outrage"}, "earliest_level": null}, {"move": {"name": "swagger"}, "earliest_level": null}, {"move": {"name": "steel-wing"}, "earliest_level": null}, {"move": {"name": "attract"}, "earliest_level": null}, {"move": {"name": "sleep-talk"}, "earliest_level": null}, {"move": {"name": "heal-bell"}, "earliest_level": null}, {"move": {"name": "return"}, "earliest_level": null}, {"move": {"name": "frustration"}, "earliest_level": null}, {"move": {"name": "safeguard"}, "earliest_level": 9}, {"move": {"name": "dragon-breath"}, "earliest_level": 1}, {"move": {"name": "iron-tail"}, "earliest_level": null}, {"move": {"name": "hidden-power"}, "earliest_level": null}, {"move": {"name": "rain-dance"}, "earliest_level": null}, {"move": {"name": "sunny-day"}, "earliest_level": null}, {"move": {"name": "psych-up"}, "earliest_level": null}, {"move": {"name": "rock-smash"}, "earliest_level": null}, {"move": {"name": "uproar"}, "earliest_level": null}, {"move": {"name": "heat-wave"}, "earliest_level": null}, {"move": {"name": "facade"}, "earliest_level": null}, {"move": {"name": "refresh"}, "earliest_level": 26}, {"move": {"name": "secret-power"}, "earliest_level": null}, {"move": {"name": "hyper-voice"}, "earliest_level": null}, {"move": {"name": "astonish"}, "earliest_level": 1}, {"move": {"name": "aerial-ace"}, "earliest_level": null}, {"move": {"name": "dragon-claw"}, "earliest_level": null}, {"move": {"name": "dragon-dance"}, "earliest_level": 30}, {"move": {"name": "roost"}, "earliest_level": null}, {"move": {"name": "natural-gift"}, "earliest_level": 20}, {"move": {"name": "pluck"}, "earliest_level": 1}, {"move": {"name": "tailwind"}, "earliest_level": null}, {"move": {"name": "dragon-pulse"}, "earliest_level": 40}, {"move": {"name": "giga-impact"}, "earliest_level": null}, {"move": {"name": "defog"}, "earliest_level": null}, {"move": {"name": "draco-meteor"}, "earliest_level": null}, {"move": {"name": "hone-claws"}, "earliest_level": null}, {"move": {"name": "wonder-room"}, "earliest_level": null}, {"move": {"name": "round"}, "earliest_level": 17}, {"move": {"name": "echoed-voice"}, "earliest_level": null}, {"move": {"name": "incinerate"}, "earliest_level": null}, {"move": {"name": "bulldoze"}, "earliest_level": null}, {"move": {"name": "cotton-guard"}, "earliest_level": 34}, {"move": {"name": "disarming-voice"}, "earliest_level": 11}, {"move": {"name": "moonblast"}, "earliest_level": 52}, {"move": {"name": "confide"}, "earliest_level": null}, {"move": {"name": "dazzling-gleam"}, "earliest_level": null}], "species": {"url": "https://pokeapi.co/api/v2/pokemon-species/334/"}, "height": 15, "weight": 206}