{"id": 10125, "name": "oricorio-sensu", "types": [{"slot": 1, "type": {"name": "ghost", "url": "https://pokeapi.co/api/v2/type/8/"}}, {"slot": 2, "type": {"name": "flying", "url": "https://pokeapi.co/api/v2/type/3/"}}], "stats": [{"base_stat": 75, "effort": 0, "stat": {"name": "hp", "url": "https://pokeapi.co/api/v2/stat/1/"}}, {"base_stat": 70, "effort": 0, "stat": {"name": "attack", "url": "https://pokeapi.co/api/v2/stat/2/"}}, {"base_stat": 70, "effort": 0, "stat": {"name": "defense", "url": "https://pokeapi.co/api/v2/stat/3/"}}, {"base_stat": 98, "effort": 2, "stat": {"name": "special-attack", "url": "https://pokeapi.co/api/v2/stat/4/"}}, {"base_stat": 70, "effort": 0, "stat": {"name": "special-defense", "url": "https://pokeapi.co/api/v2/stat/5/"}}, {"base_stat": 93, "effort": 0, "stat": {"name": "speed", "url": "https://pokeapi.co/api/v2/stat/6/"}}], "abilities": [{"ability": {"name": "dancer", "url": "https://pokeapi.co/api/v2/ability/216/"}, "is_hidden": false, "slot": 1}], "sprites": {"front_default": "https://raw.githubusercontent.com/PokeAPI/sprites/master/sprites/pokemon/10125.png"}, "moves": [{"move": {"name": "pound"}, "earliest_level": 1}, {"move": {"name": "double-slap"}, "earliest_level": 23}, {"move": {"name": "swords-dance"}, "earliest_level": null}, {"move": {"name": "fly"}, "earliest_level": null}, {"move": {"name": "take-down"}, "earliest_level": null}, {"move": {"name": "growl"}, "earliest_level": 4}, {"move": {"name": "peck"}, "earliest_level": 6}, {"move": {"name": "toxic"}, "earliest_level": null}, {"move": {"name": "agility"}, "earliest_level": 43}, {"move": {"name": "double-team"}, "earliest_level": null}, {"move": {"name": "mirror-move"}, "earliest_level": 43}, {"move": {"name": "swift"}, "earliest_level": null}, {"move": {"name": "sky-attack"}, "earliest_level": null}, {"move": {"name": "rest"}, "earliest_level": null}, {"move": {"name": "substitute"}, "earliest_level": null}, {"move": {"name": "snore"}, "earliest_level": null}, {"move": {"name": "reversal"}, "earliest_level": null}, {"move": {"name": "protect"}, "earliest_level": null}, {"move": {"name": "icy-wind"}, "earliest_level": null}, {"move": {"name": "sandstorm"}, "earliest_level": null}, {"move": {"name": "endure"}, "earliest_level": null}, {"move": {"name": "charm"}, "earliest_level": null}, {"move": {"name": "swagger"}, "earliest_level": null}, {"move": {"name": "steel-wing"}, "earliest_level": null}, {"move": {"name": "attract"}, "earliest_level": null}, {"move": {"name": "sleep-talk"}, "earliest_level": null}, {"move": {"name": "return"}, "earliest_level": null}, {"move": {"name": "frustration"}, "earliest_level": null}, {"move": {"name": "safeguard"}, "earliest_level": null}, {"move": {"name": "baton-pass"}, "earliest_level": 16}, {"move": {"name": "hidden-power"}, "earliest_level": null}, {"move": {"name": "rain-dance"}, "earliest_level": null}, {"move": {"name": "sunny-day"}, "earliest_level": null}, {"move": {"name": "psych-up"}, "earliest_level": null}, {"move": {"name": "flatter"}, "earliest_level": 33}, {"move": {"name": "facade"}, "earliest_level": null}, {"move": {"name": "taunt"}, "earliest_level": null}, {"move": {"name": "helping-hand"}, "earliest_level": 10}, {"move": {"name": "role-play"}, "earliest_level": null}, {"move": {"name": "feather-dance"}, "earliest_level": 20}, {"move": {"name": "teeter-dance"}, "earliest_level": 26}, {"move": {"name": "air-cutter"}, "earliest_level": 13}, {"move": {"name": "aerial-ace"}, "earliest_level": null}, {"move": {"name": "covet"}, "earliest_level": null}, {"move": {"name": "calm-mind"}, "earliest_level": null}, {"move": {"name": "roost"}, "earliest_level": 30}, {"move": {"name": "pluck"}, "earliest_level": null}, {"move": {"name": "tailwind"}, "earliest_level": null}, {"move": {"name": "u-turn"}, "earliest_level": null}, {"move": {"name": "embargo"}, "earliest_level": null}, {"move": {"name": "air-slash"}, "earliest_level": 36}, {"move": {"name": "defog"}, "earliest_level": null}, {"move": {"name": "captivate"}, "earliest_level": 33}, {"move": {"name": "quiver-dance"}, "earliest_level": null}, {"move": {"name": "round"}, "earliest_level": null}, {"move": {"name": "quash"}, "earliest_level": null}, {"move": {"name": "acrobatics"}, "earliest_level": 23}, {"move": {"name": "work-up"}, "earliest_level": null}, {"move": {"name": "hurricane"}, "earliest_level": 47}, {"move": {"name": "confide"}, "earliest_level": null}, {"move": {"name": "revelation-dance"}, "earliest_level": 40}, {"move": {"name": "dual-wingbeat"}, "earliest_level": null}, {"move": {"name": "tera-blast"}, "earliest_level": null}, {"move": {"name": "trailblaze"}, "earliest_level": null}, {"move": {"name": "alluring-voice"}, "earliest_level": null}], "species": {"url": "https://pokeapi.co/api/v2/pokemon-species/741/"}, "height": 6, "weight": 34}