{"id": 165, "name": "ledyba", "types": [{"slot": 1, "type": {"name": "bug", "url": "https://pokeapi.co/api/v2/type/7/"}}, {"slot": 2, "type": {"name": "flying", "url": "https://pokeapi.co/api/v2/type/3/"}}], "stats": [{"base_stat": 40, "effort": 0, "stat": {"name": "hp", "url": "https://pokeapi.co/api/v2/stat/1/"}}, {"base_stat": 20, "effort": 0, "stat": {"name": "attack", "url": "https://pokeapi.co/api/v2/stat/2/"}}, {"base_stat": 30, "effort": 0, "stat": {"name": "defense", "url": "https://pokeapi.co/api/v2/stat/3/"}}, {"base_stat": 40, "effort": 0, "stat": {"name": "special-attack", "url": "https://pokeapi.co/api/v2/stat/4/"}}, {"base_stat": 80, "effort": 1, "stat": {"name": "special-defense", "url": "https://pokeapi.co/api/v2/stat/5/"}}, {"base_stat": 55, "effort": 0, "stat": {"name": "speed", "url": "https://pokeapi.co/api/v2/stat/6/"}}], "abilities": [{"ability": {"name": "swarm", "url": "https://pokeapi.co/api/v2/ability/68/"}, "is_hidden": false, "slot": 1}, {"ability": {"name": "early-bird", "url": "https://pokeapi.co/api/v2/ability/48/"}, "is_hidden": false, "slot": 2}, {"ability": {"name": "rattled", "url": "https://pokeapi.co/api/v2/ability/155/"}, "is_hidden": true, "slot": 3}], "sprites": {"front_default": "https://raw.githubusercontent.com/PokeAPI/sprites/master/sprites/pokemon/165.png"}, "moves": [{"move": {"name": "comet-punch"}, "earliest_level": 9}, {"move": {"name": "mega-punch"}, "earliest_level": null}, {"move": {"name": "ice-punch"}, "earliest_level": null}, {"move": {"name": "thunder-punch"}, "earliest_level": null}, {"move": {"name": "swords-dance"}, "earliest_level": null}, {"move": {"name": "headbutt"}, "earliest_level": null}, {"move": {"name": "tackle"}, "earliest_level": 1}, {"move": {"name": "double-edge"}, "earliest_level": 38}, {"move": {"name": "supersonic"}, "earliest_level": 5}, {"move": {"name": "psybeam"}, "earliest_level": null}, {"move": {"name": "counter"}, "earliest_level": null}, {"move": {"name": "solar-beam"}, "earliest_level": null}, {"move": {"name": "string-shot"}, "earliest_level": null}, {"move": {"name": "dig"}, "earliest_level": null}, {"move": {"name": "toxic"}, "earliest_level": null}, {"move": {"name": "agility"}, "earliest_level": 29}, {"move": {"name": "mimic"}, "earliest_level": null}, {"move": {"name": "screech"}, "earliest_level": null}, {"move": {"name": "double-team"}, "earliest_level": null}, {"move": {"name": "light-screen"}, "earliest_level": 12}, {"move": {"name": "reflect"}, "earliest_level": 12}, {"move": {"name": "bide"}, "earliest_level": null}, {"move": {"name": "swift"}, "earliest_level": 8}, {"move": {"name": "dizzy-punch"}, "earliest_level": null}, {"move": {"name": "flash"}, "earliest_level": null}, {"move": {"name": "rest"}, "earliest_level": null}, {"move": {"name": "substitute"}, "earliest_level": null}, {"move": {"name": "thief"}, "earliest_level": null}, {"move": {"name": "snore"}, "earliest_level": null}, {"move": {"name": "curse"}, "earliest_level": null}, {"move": {"name": "protect"}, "earliest_level": null}, {"move": {"name": "mach-punch"}, "earliest_level": 15}, {"move": {"name": "giga-drain"}, "earliest_level": null}, {"move": {"name": "endure"}, "earliest_level": null}, {"move": {"name": "rollout"}, "earliest_level": null}, {"move": {"name": "swagger"}, "earliest_level": null}, {"move": {"name": "attract"}, "earliest_level": null}, {"move": {"name": "sleep-talk"}, "earliest_level": null}, {"move": {"name": "return"}, "earliest_level": null}, {"move": {"name": "frustration"}, "earliest_level": null}, {"move": {"name": "safeguard"}, "earliest_level": 12}, {"move": {"name": "dynamic-punch"}, "earliest_level": null}, {"move": {"name": "baton-pass"}, "earliest_level": 22}, {"move": {"name": "encore"}, "earliest_level": null}, {"move": {"name": "sweet-scent"}, "earliest_level": null}, {"move": {"name": "hidden-power"}, "earliest_level": null}, {"move": {"name": "sunny-day"}, "earliest_level": null}, {"move": {"name": "uproar"}, "earliest_level": null}, {"move": {"name": "facade"}, "earliest_level": null}, {"move": {"name": "focus-punch"}, "earliest_level": null}, {"move": {"name": "brick-break"}, "earliest_level": null}, {"move": {"name": "knock-off"}, "earliest_level": null}, {"move": {"name": "secret-power"}, "earliest_level": null}, {"move": {"name": "air-cutter"}, "earliest_level": null}, {"move": {"name": "silver-wind"}, "earliest_level": 19}, {"move": {"name": "aerial-ace"}, "earliest_level": null}, {"move": {"name": "roost"}, "earliest_level": 19}, {"move": {"name": "natural-gift"}, "earliest_level": null}, {"move": {"name": "tailwind"}, "earliest_level": null}, {"move": {"name": "u-turn"}, "earliest_level": null}, {"move": {"name": "fling"}, "earliest_level": null}, {"move": {"name": "air-slash"}, "earliest_level": 36}, {"move": {"name": "bug-buzz"}, "earliest_level": 33}, {"move": {"name": "drain-punch"}, "earliest_level": null}, {"move": {"name": "captivate"}, "earliest_level": null}, {"move": {"name": "bug-bite"}, "earliest_level": null}, {"move": {"name": "ominous-wind"}, "earliest_level": null}, {"move": {"name": "round"}, "earliest_level": null}, {"move": {"name": "acrobatics"}, "earliest_level": null}, {"move": {"name": "struggle-bug"}, "earliest_level": 22}, {"move": {"name": "confide"}, "earliest_level": null}, {"move": {"name": "infestation"}, "earliest_level": null}, {"move": {"name": "power-up-punch"}, "earliest_level": null}], "species": {"url": "https://pokeapi.co/api/v2/pokemon-species/165/"}, "height": 10, "weight": 108}