{"id": 219, "name": "magcargo", "types": [{"slot": 1, "type": {"name": "fire", "url": "https://pokeapi.co/api/v2/type/10/"}}, {"slot": 2, "type": {"name": "rock", "url": "https://pokeapi.co/api/v2/type/6/"}}], "stats": [{"base_stat": 60, "effort": 0, "stat": {"name": "hp", "url": "https://pokeapi.co/api/v2/stat/1/"}}, {"base_stat": 50, "effort": 0, "stat": {"name": "attack", "url": "https://pokeapi.co/api/v2/stat/2/"}}, {"base_stat": 120, "effort": 2, "stat": {"name": "defense", "url": "https://pokeapi.co/api/v2/stat/3/"}}, {"base_stat": 90, "effort": 0, "stat": {"name": "special-attack", "url": "https://pokeapi.co/api/v2/stat/4/"}}, {"base_stat": 80, "effort": 0, "stat": {"name": "special-defense", "url": "https://pokeapi.co/api/v2/stat/5/"}}, {"base_stat": 30, "effort": 0, "stat": {"name": "speed", "url": "https://pokeapi.co/api/v2/stat/6/"}}], "abilities": [{"ability": {"name": "magma-armor", "url": "https://pokeapi.co/api/v2/ability/40/"}, "is_hidden": false, "slot": 1}, {"ability": {"name": "flame-body", "url": "https://pokeapi.co/api/v2/ability/49/"}, "is_hidden": false, "slot": 2}, {"ability": {"name": "weak-armor", "url": "https://pokeapi.co/api/v2/ability/133/"}, "is_hidden": true, "slot": 3}], "sprites": {"front_default": "https://raw.githubusercontent.com/PokeAPI/sprites/master/sprites/pokemon/219.png"}, "moves": [{"move": {"name": "body-slam"}, "earliest_level": 43}, {"move": {"name": "take-down"}, "earliest_level": null}, {"move": {"name": "double-edge"}, "earliest_level": null}, {"move": {"name": "ember"}, "earliest_level": 1}, {"move": {"name": "flamethrower"}, "earliest_level": 36}, {"move": {"name": "hyper-beam"}, "earliest_level": null}, {"move": {"name": "strength"}, "earliest_level": null}, {"move": {"name": "solar-beam"}, "earliest_level": null}, {"move": {"name": "fire-spin"}, "earliest_level": null}, {"move": {"name": "rock-throw"}, "earliest_level": 1}, {"move": {"name": "earthquake"}, "earliest_level": null}, {"move": {"name": "toxic"}, "earliest_level": null}, {"move": {"name": "mimic"}, "earliest_level": null}, {"move": {"name": "double-team"}, "earliest_level": null}, {"move": {"name": "recover"}, "earliest_level": 19}, {"move": {"name": "harden"}, "earliest_level": 13}, {"move": {"name": "smokescreen"}, "earliest_level": null}, {"move": {"name": "defense-curl"}, "earliest_level": null}, {"move": {"name": "light-screen"}, "earliest_level": null}, {"move": {"name": "reflect"}, "earliest_level": null}, {"move": {"name": "self-destruct"}, "earliest_level": null}, {"move": {"name": "smog"}, "earliest_level": 1}, {"move": {"name": "fire-blast"}, "earliest_level": null}, {"move": {"name": "amnesia"}, "earliest_level": 29}, {"move": {"name": "acid-armor"}, "earliest_level": null}, {"move": {"name": "explosion"}, "earliest_level": null}, {"move": {"name": "rest"}, "earliest_level": null}, {"move": {"name": "rock-slide"}, "earliest_level": 29}, {"move": {"name": "substitute"}, "earliest_level": null}, {"move": {"name": "snore"}, "earliest_level": null}, {"move": {"name": "curse"}, "earliest_level": null}, {"move": {"name": "protect"}, "earliest_level": null}, {"move": {"name": "mud-slap"}, "earliest_level": null}, {"move": {"name": "sandstorm"}, "earliest_level": null}, {"move": {"name": "endure"}, "earliest_level": null}, {"move": {"name": "rollout"}, "earliest_level": null}, {"move": {"name": "swagger"}, "earliest_level": null}, {"move": {"name": "attract"}, "earliest_level": null}, {"move": {"name": "sleep-talk"}, "earliest_level": null}, {"move": {"name": "return"}, "earliest_level": null}, {"move": {"name": "frustration"}, "earliest_level": null}, {"move": {"name": "pain-split"}, "earliest_level": null}, {"move": {"name": "hidden-power"}, "earliest_level": null}, {"move": {"name": "sunny-day"}, "earliest_level": null}, {"move": {"name": "ancient-power"}, "earliest_level": 22}, {"move": {"name": "rock-smash"}, "earliest_level": null}, {"move": {"name": "stockpile"}, "earliest_level": null}, {"move": {"name": "heat-wave"}, "earliest_level": null}, {"move": {"name": "will-o-wisp"}, "earliest_level": null}, {"move": {"name": "memento"}, "earliest_level": null}, {"move": {"name": "facade"}, "earliest_level": null}, {"move": {"name": "nature-power"}, "earliest_level": null}, {"move": {"name": "yawn"}, "earliest_level": 1}, {"move": {"name": "secret-power"}, "earliest_level": null}, {"move": {"name": "overheat"}, "earliest_level": null}, {"move": {"name": "rock-tomb"}, "earliest_level": null}, {"move": {"name": "sand-tomb"}, "earliest_level": null}, {"move": {"name": "iron-defense"}, "earliest_level": null}, {"move": {"name": "mud-shot"}, "earliest_level": null}, {"move": {"name": "rock-blast"}, "earliest_level": null}, {"move": {"name": "gyro-ball"}, "earliest_level": null}, {"move": {"name": "natural-gift"}, "earliest_level": null}, {"move": {"name": "guard-swap"}, "earliest_level": null}, {"move": {"name": "flare-blitz"}, "earliest_level": null}, {"move": {"name": "rock-polish"}, "earliest_level": null}, {"move": {"name": "power-gem"}, "earliest_level": null}, {"move": {"name": "earth-power"}, "earliest_level": 1}, {"move": {"name": "giga-impact"}, "earliest_level": null}, {"move": {"name": "lava-plume"}, "earliest_level": 34}, {"move": {"name": "stone-edge"}, "earliest_level": null}, {"move": {"name": "captivate"}, "earliest_level": null}, {"move": {"name": "stealth-rock"}, "earliest_level": null}, {"move": {"name": "smack-down"}, "earliest_level": null}, {"move": {"name": "flame-burst"}, "earliest_level": 23}, {"move": {"name": "flame-charge"}, "earliest_level": null}, {"move": {"name": "after-you"}, "earliest_level": null}, {"move": {"name": "round"}, "earliest_level": null}, {"move": {"name": "clear-smog"}, "earliest_level": 20}, {"move": {"name": "shell-smash"}, "earliest_level": 1}, {"move": {"name": "incinerate"}, "earliest_level": 15}, {"move": {"name": "inferno"}, "earliest_level": null}, {"move": {"name": "bulldoze"}, "earliest_level": null}, {"move": {"name": "heat-crash"}, "earliest_level": null}, {"move": {"name": "confide"}, "earliest_level": null}, {"move": {"name": "infestation"}, "earliest_level": null}, {"move": {"name": "stomping-tantrum"}, "earliest_level": null}, {"move": {"name": "burning-jealousy"}, "earliest_level": null}, {"move": {"name": "scorching-sands"}, "earliest_level": null}, {"move": {"name": "tera-blast"}, "earliest_level": null}, {"move": {"name": "temper-flare"}, "earliest_level": null}], "species": {"url": "https://pokeapi.co/api/v2/pokemon-species/219/"}, "height": 8, "weight": 550}